sequana_pipelines/demultiplex/__init__.py
sequana_pipelines/demultiplex/config.yaml
sequana_pipelines/demultiplex/dag.png
sequana_pipelines/demultiplex/demultiplex.rules
sequana_pipelines/demultiplex/logo.png
sequana_pipelines/demultiplex/main.py
sequana_pipelines/demultiplex/multiqc_config.yaml
sequana_pipelines/demultiplex/schema.yaml
sequana_pipelines/demultiplex/tools.txt
sequana_demultiplex-1.5.2.dist-info/LICENSE
sequana_demultiplex-1.5.2.dist-info/METADATA
sequana_demultiplex-1.5.2.dist-info/WHEEL
sequana_demultiplex-1.5.2.dist-info/entry_points.txt
sequana_demultiplex-1.5.2.dist-info/RECORD
